[
  {
    "date": "2024-02-12",
    "act_symbol": "SPY",
    "expiration": "2024-02-26",
    "strike": "450.00",
    "call_put": "Call",
    "bid": "51.37",
    "ask": "51.70",
    "vol": "0.2728",
    "delta": "0.9798",
    "gamma": "0.0018",
    "theta": "-0.1093",
    "vega": "0.0475",
    "rho": "0.1683"
  },
  {
    "date": "2024-02-12",
    "act_symbol": "SPY",
    "expiration": "2024-02-26",
    "strike": "450.00",
    "call_put": "Put",
    "bid": "0.13",
    "ask": "0.14",
    "vol": "0.2572",
    "delta": "-0.0148",
    "gamma": "0.0014",
    "theta": "-0.0327",
    "vega": "0.0368",
    "rho": "-0.0029"
  },
  {
    "date": "2024-02-12",
    "act_symbol": "SPY",
    "expiration": "2024-02-26",
    "strike": "460.00",
    "call_put": "Call",
    "bid": "41.42",
    "ask": "41.76",
    "vol": "0.2309",
    "delta": "0.9731",
    "gamma": "0.0027",
    "theta": "-0.1140",
    "vega": "0.0607",
    "rho": "0.1708"
  },
  {
    "date": "2024-02-12",
    "act_symbol": "SPY",
    "expiration": "2024-02-26",
    "strike": "460.00",
    "call_put": "Put",
    "bid": "0.16",
    "ask": "0.17",
    "vol": "0.2181",
    "delta": "-0.0206",
    "gamma": "0.0023",
    "theta": "-0.0364",
    "vega": "0.0487",
    "rho": "-0.0040"
  },
  {
    "date": "2024-02-12",
    "act_symbol": "SPY",
    "expiration": "2024-02-26",
    "strike": "470.00",
    "call_put": "Call",
    "bid": "31.50",
    "ask": "31.84",
    "vol": "0.1894",
    "delta": "0.9610",
    "gamma": "0.0045",
    "theta": "-0.1204",
    "vega": "0.0825",
    "rho": "0.1723"
  },
  {
    "date": "2024-02-12",
    "act_symbol": "SPY",
    "expiration": "2024-02-26",
    "strike": "470.00",
    "call_put": "Put",
    "bid": "0.22",
    "ask": "0.23",
    "vol": "0.1804",
    "delta": "-0.0321",
    "gamma": "0.0040",
    "theta": "-0.0431",
    "vega": "0.0706",
    "rho": "-0.0062"
  },
  {
    "date": "2024-02-12",
    "act_symbol": "SPY",
    "expiration": "2024-02-26",
    "strike": "480.00",
    "call_put": "Call",
    "bid": "21.68",
    "ask": "22.01",
    "vol": "0.1512",
    "delta": "0.9319",
    "gamma": "0.0088",
    "theta": "-0.1334",
    "vega": "0.1287",
    "rho": "0.1705"
  },
  {
    "date": "2024-02-12",
    "act_symbol": "SPY",
    "expiration": "2024-02-26",
    "strike": "480.00",
    "call_put": "Put",
    "bid": "0.37",
    "ask": "0.38",
    "vol": "0.1450",
    "delta": "-0.0604",
    "gamma": "0.0084",
    "theta": "-0.0567",
    "vega": "0.1266",
    "rho": "-0.0108"
  },
  {
    "date": "2024-02-12",
    "act_symbol": "SPY",
    "expiration": "2024-02-26",
    "strike": "491.00",
    "call_put": "Call",
    "bid": "11.51",
    "ask": "11.63",
    "vol": "0.1189",
    "delta": "0.8198",
    "gamma": "0.0225",
    "theta": "-0.1666",
    "vega": "0.2572",
    "rho": "0.1529"
  },
  {
    "date": "2024-02-12",
    "act_symbol": "SPY",
    "expiration": "2024-02-26",
    "strike": "491.00",
    "call_put": "Put",
    "bid": "1.09",
    "ask": "1.11",
    "vol": "0.1163",
    "delta": "-0.1775",
    "gamma": "0.0231",
    "theta": "-0.0944",
    "vega": "0.2635",
    "rho": "-0.0304"
  },
  {
    "date": "2024-02-12",
    "act_symbol": "SPY",
    "expiration": "2024-02-26",
    "strike": "501.00",
    "call_put": "Call",
    "bid": "4.26",
    "ask": "4.29",
    "vol": "0.1037",
    "delta": "0.5212",
    "gamma": "0.0392",
    "theta": "-0.1814",
    "vega": "0.3904",
    "rho": "0.0984"
  },
  {
    "date": "2024-02-12",
    "act_symbol": "SPY",
    "expiration": "2024-02-26",
    "strike": "501.00",
    "call_put": "Put",
    "bid": "3.84",
    "ask": "3.87",
    "vol": "0.1018",
    "delta": "-0.4936",
    "gamma": "0.0422",
    "theta": "-0.1139",
    "vega": "0.3887",
    "rho": "-0.0720"
  },
  {
    "date": "2024-02-12",
    "act_symbol": "SPY",
    "expiration": "2024-02-26",
    "strike": "510.00",
    "call_put": "Call",
    "bid": "1.03",
    "ask": "1.05",
    "vol": "0.0993",
    "delta": "0.1946",
    "gamma": "0.0283",
    "theta": "-0.1095",
    "vega": "0.2699",
    "rho": "0.0369"
  },
  {
    "date": "2024-02-12",
    "act_symbol": "SPY",
    "expiration": "2024-02-26",
    "strike": "510.00",
    "call_put": "Put",
    "bid": "9.87",
    "ask": "10.00",
    "vol": "0.0992",
    "delta": "-0.8536",
    "gamma": "0.0333",
    "theta": "-0.0496",
    "vega": "0.2312",
    "rho": "-0.0656"
  },
  {
    "date": "2024-02-12",
    "act_symbol": "SPY",
    "expiration": "2024-02-26",
    "strike": "520.00",
    "call_put": "Call",
    "bid": "0.12",
    "ask": "0.13",
    "vol": "0.1154",
    "delta": "0.0552",
    "gamma": "0.0098",
    "theta": "-0.0490",
    "vega": "0.1094",
    "rho": "0.0105"
  },
  {
    "date": "2024-02-12",
    "act_symbol": "SPY",
    "expiration": "2024-02-26",
    "strike": "520.00",
    "call_put": "Put",
    "bid": "19.39",
    "ask": "19.72",
    "vol": "0.1154",
    "delta": "-1.0000",
    "gamma": "0.0014",
    "theta": "0.0000",
    "vega": "0.0040",
    "rho": "0.0000"
  },
  {
    "date": "2024-02-12",
    "act_symbol": "SPY",
    "expiration": "2024-02-26",
    "strike": "530.00",
    "call_put": "Call",
    "bid": "0.03",
    "ask": "0.04",
    "vol": "0.1316",
    "delta": "0.0163",
    "gamma": "0.0031",
    "theta": "-0.0199",
    "vega": "0.0399",
    "rho": "0.0031"
  },
  {
    "date": "2024-02-12",
    "act_symbol": "SPY",
    "expiration": "2024-02-26",
    "strike": "530.00",
    "call_put": "Put",
    "bid": "29.39",
    "ask": "29.72",
    "vol": "0.1316",
    "delta": "-1.0000",
    "gamma": "0.0000",
    "theta": "0.0000",
    "vega": "0.0000",
    "rho": "0.0000"
  },
  {
    "date": "2024-02-12",
    "act_symbol": "SPY",
    "expiration": "2024-02-26",
    "strike": "540.00",
    "call_put": "Call",
    "bid": "0.02",
    "ask": "0.03",
    "vol": "0.1478",
    "delta": "0.0054",
    "gamma": "0.0010",
    "theta": "-0.0084",
    "vega": "0.0153",
    "rho": "0.0010"
  },
  {
    "date": "2024-02-12",
    "act_symbol": "SPY",
    "expiration": "2024-02-26",
    "strike": "540.00",
    "call_put": "Put",
    "bid": "39.39",
    "ask": "39.72",
    "vol": "0.1478",
    "delta": "-1.0000",
    "gamma": "0.0000",
    "theta": "0.0000",
    "vega": "0.0000",
    "rho": "0.0000"
  },
  {
    "date": "2024-02-12",
    "act_symbol": "SPY",
    "expiration": "2024-02-26",
    "strike": "550.00",
    "call_put": "Call",
    "bid": "0.01",
    "ask": "0.02",
    "vol": "0.1757",
    "delta": "0.0038",
    "gamma": "0.0006",
    "theta": "-0.0072",
    "vega": "0.0111",
    "rho": "0.0007"
  },
  {
    "date": "2024-02-12",
    "act_symbol": "SPY",
    "expiration": "2024-02-26",
    "strike": "550.00",
    "call_put": "Put",
    "bid": "49.39",
    "ask": "49.72",
    "vol": "0.1757",
    "delta": "-1.0000",
    "gamma": "0.0000",
    "theta": "0.0000",
    "vega": "0.0000",
    "rho": "0.0000"
  },
  {
    "date": "2024-02-12",
    "act_symbol": "SPY",
    "expiration": "2024-03-08",
    "strike": "350.00",
    "call_put": "Call",
    "bid": "151.77",
    "ask": "152.14",
    "vol": "0.5991",
    "delta": "0.9913",
    "gamma": "0.0002",
    "theta": "-0.0874",
    "vega": "0.0306",
    "rho": "0.2357"
  },
  {
    "date": "2024-02-12",
    "act_symbol": "SPY",
    "expiration": "2024-03-08",
    "strike": "350.00",
    "call_put": "Put",
    "bid": "0.04",
    "ask": "0.05",
    "vol": "0.4974",
    "delta": "-0.0022",
    "gamma": "0.0001",
    "theta": "-0.0090",
    "vega": "0.0092",
    "rho": "-0.0008"
  },
  {
    "date": "2024-02-12",
    "act_symbol": "SPY",
    "expiration": "2024-03-08",
    "strike": "365.00",
    "call_put": "Call",
    "bid": "136.85",
    "ask": "137.22",
    "vol": "0.5437",
    "delta": "0.9896",
    "gamma": "0.0003",
    "theta": "-0.0918",
    "vega": "0.0358",
    "rho": "0.2453"
  },
  {
    "date": "2024-02-12",
    "act_symbol": "SPY",
    "expiration": "2024-03-08",
    "strike": "365.00",
    "call_put": "Put",
    "bid": "0.06",
    "ask": "0.07",
    "vol": "0.4611",
    "delta": "-0.0034",
    "gamma": "0.0001",
    "theta": "-0.0121",
    "vega": "0.0134",
    "rho": "-0.0012"
  },
  {
    "date": "2024-02-12",
    "act_symbol": "SPY",
    "expiration": "2024-03-08",
    "strike": "375.00",
    "call_put": "Call",
    "bid": "126.91",
    "ask": "127.27",
    "vol": "0.5074",
    "delta": "0.9883",
    "gamma": "0.0004",
    "theta": "-0.0947",
    "vega": "0.0400",
    "rho": "0.2517"
  },
  {
    "date": "2024-02-12",
    "act_symbol": "SPY",
    "expiration": "2024-03-08",
    "strike": "375.00",
    "call_put": "Put",
    "bid": "0.07",
    "ask": "0.08",
    "vol": "0.4320",
    "delta": "-0.0041",
    "gamma": "0.0002",
    "theta": "-0.0134",
    "vega": "0.0159",
    "rho": "-0.0014"
  },
  {
    "date": "2024-02-12",
    "act_symbol": "SPY",
    "expiration": "2024-03-08",
    "strike": "390.00",
    "call_put": "Call",
    "bid": "112.00",
    "ask": "112.36",
    "vol": "0.4545",
    "delta": "0.9856",
    "gamma": "0.0006",
    "theta": "-0.0997",
    "vega": "0.0478",
    "rho": "0.2610"
  },
  {
    "date": "2024-02-12",
    "act_symbol": "SPY",
    "expiration": "2024-03-08",
    "strike": "390.00",
    "call_put": "Put",
    "bid": "0.10",
    "ask": "0.11",
    "vol": "0.3940",
    "delta": "-0.0061",
    "gamma": "0.0003",
    "theta": "-0.0173",
    "vega": "0.0226",
    "rho": "-0.0021"
  },
  {
    "date": "2024-02-12",
    "act_symbol": "SPY",
    "expiration": "2024-03-08",
    "strike": "400.00",
    "call_put": "Call",
    "bid": "102.06",
    "ask": "102.42",
    "vol": "0.4190",
    "delta": "0.9834",
    "gamma": "0.0007",
    "theta": "-0.1026",
    "vega": "0.0539",
    "rho": "0.2671"
  },
  {
    "date": "2024-02-12",
    "act_symbol": "SPY",
    "expiration": "2024-03-08",
    "strike": "400.00",
    "call_put": "Put",
    "bid": "0.12",
    "ask": "0.13",
    "vol": "0.3661",
    "delta": "-0.0076",
    "gamma": "0.0004",
    "theta": "-0.0196",
    "vega": "0.0276",
    "rho": "-0.0027"
  },
  {
    "date": "2024-02-12",
    "act_symbol": "SPY",
    "expiration": "2024-03-08",
    "strike": "415.00",
    "call_put": "Call",
    "bid": "87.16",
    "ask": "87.52",
    "vol": "0.3668",
    "delta": "0.9791",
    "gamma": "0.0010",
    "theta": "-0.1076",
    "vega": "0.0657",
    "rho": "0.2758"
  },
  {
    "date": "2024-02-12",
    "act_symbol": "SPY",
    "expiration": "2024-03-08",
    "strike": "415.00",
    "call_put": "Put",
    "bid": "0.15",
    "ask": "0.16",
    "vol": "0.3219",
    "delta": "-0.0105",
    "gamma": "0.0006",
    "theta": "-0.0226",
    "vega": "0.0364",
    "rho": "-0.0037"
  },
  {
    "date": "2024-02-12",
    "act_symbol": "SPY",
    "expiration": "2024-03-08",
    "strike": "425.00",
    "call_put": "Call",
    "bid": "77.23",
    "ask": "77.59",
    "vol": "0.3319",
    "delta": "0.9753",
    "gamma": "0.0013",
    "theta": "-0.1107",
    "vega": "0.0755",
    "rho": "0.2813"
  },
  {
    "date": "2024-02-12",
    "act_symbol": "SPY",
    "expiration": "2024-03-08",
    "strike": "425.00",
    "call_put": "Put",
    "bid": "0.18",
    "ask": "0.19",
    "vol": "0.2934",
    "delta": "-0.0134",
    "gamma": "0.0008",
    "theta": "-0.0254",
    "vega": "0.0450",
    "rho": "-0.0047"
  },
  {
    "date": "2024-02-12",
    "act_symbol": "SPY",
    "expiration": "2024-03-08",
    "strike": "440.00",
    "call_put": "Call",
    "bid": "62.38",
    "ask": "62.72",
    "vol": "0.2819",
    "delta": "0.9664",
    "gamma": "0.0020",
    "theta": "-0.1172",
    "vega": "0.0977",
    "rho": "0.2884"
  },
  {
    "date": "2024-02-12",
    "act_symbol": "SPY",
    "expiration": "2024-03-08",
    "strike": "440.00",
    "call_put": "Put",
    "bid": "0.25",
    "ask": "0.26",
    "vol": "0.2517",
    "delta": "-0.0205",
    "gamma": "0.0015",
    "theta": "-0.0310",
    "vega": "0.0648",
    "rho": "-0.0072"
  },
  {
    "date": "2024-02-12",
    "act_symbol": "SPY",
    "expiration": "2024-03-08",
    "strike": "450.00",
    "call_put": "Call",
    "bid": "52.49",
    "ask": "52.83",
    "vol": "0.2482",
    "delta": "0.9576",
    "gamma": "0.0027",
    "theta": "-0.1215",
    "vega": "0.1181",
    "rho": "0.2922"
  },
  {
    "date": "2024-02-12",
    "act_symbol": "SPY",
    "expiration": "2024-03-08",
    "strike": "450.00",
    "call_put": "Put",
    "bid": "0.32",
    "ask": "0.33",
    "vol": "0.2237",
    "delta": "-0.0282",
    "gamma": "0.0022",
    "theta": "-0.0358",
    "vega": "0.0848",
    "rho": "-0.0099"
  },
  {
    "date": "2024-02-12",
    "act_symbol": "SPY",
    "expiration": "2024-03-08",
    "strike": "460.00",
    "call_put": "Call",
    "bid": "42.70",
    "ask": "42.86",
    "vol": "0.2132",
    "delta": "0.9456",
    "gamma": "0.0039",
    "theta": "-0.1250",
    "vega": "0.1443",
    "rho": "0.2948"
  },
  {
    "date": "2024-02-12",
    "act_symbol": "SPY",
    "expiration": "2024-03-08",
    "strike": "460.00",
    "call_put": "Put",
    "bid": "0.43",
    "ask": "0.44",
    "vol": "0.1959",
    "delta": "-0.0409",
    "gamma": "0.0034",
    "theta": "-0.0422",
    "vega": "0.1237",
    "rho": "-0.0133"
  },
  {
    "date": "2024-02-12",
    "act_symbol": "SPY",
    "expiration": "2024-03-08",
    "strike": "471.00",
    "call_put": "Call",
    "bid": "31.99",
    "ask": "32.15",
    "vol": "0.1801",
    "delta": "0.9173",
    "gamma": "0.0064",
    "theta": "-0.1348",
    "vega": "0.1995",
    "rho": "0.2925"
  },
  {
    "date": "2024-02-12",
    "act_symbol": "SPY",
    "expiration": "2024-03-08",
    "strike": "471.00",
    "call_put": "Put",
    "bid": "0.67",
    "ask": "0.68",
    "vol": "0.1674",
    "delta": "-0.0686",
    "gamma": "0.0060",
    "theta": "-0.0533",
    "vega": "0.1831",
    "rho": "-0.0219"
  },
  {
    "date": "2024-02-12",
    "act_symbol": "SPY",
    "expiration": "2024-03-08",
    "strike": "481.00",
    "call_put": "Call",
    "bid": "22.53",
    "ask": "22.67",
    "vol": "0.1531",
    "delta": "0.8644",
    "gamma": "0.0108",
    "theta": "-0.1477",
    "vega": "0.2852",
    "rho": "0.2808"
  },
  {
    "date": "2024-02-12",
    "act_symbol": "SPY",
    "expiration": "2024-03-08",
    "strike": "481.00",
    "call_put": "Put",
    "bid": "1.17",
    "ask": "1.18",
    "vol": "0.1443",
    "delta": "-0.1238",
    "gamma": "0.0109",
    "theta": "-0.0689",
    "vega": "0.2778",
    "rho": "-0.0386"
  },
  {
    "date": "2024-02-12",
    "act_symbol": "SPY",
    "expiration": "2024-03-08",
    "strike": "491.00",
    "call_put": "Call",
    "bid": "13.77",
    "ask": "13.87",
    "vol": "0.1310",
    "delta": "0.7515",
    "gamma": "0.0184",
    "theta": "-0.1621",
    "vega": "0.4148",
    "rho": "0.2481"
  },
  {
    "date": "2024-02-12",
    "act_symbol": "SPY",
    "expiration": "2024-03-08",
    "strike": "491.00",
    "call_put": "Put",
    "bid": "2.37",
    "ask": "2.39",
    "vol": "0.1248",
    "delta": "-0.2445",
    "gamma": "0.0197",
    "theta": "-0.0869",
    "vega": "0.4189",
    "rho": "-0.0720"
  },
  {
    "date": "2024-02-12",
    "act_symbol": "SPY",
    "expiration": "2024-03-08",
    "strike": "501.00",
    "call_put": "Call",
    "bid": "6.70",
    "ask": "6.73",
    "vol": "0.1161",
    "delta": "0.5394",
    "gamma": "0.0261",
    "theta": "-0.1595",
    "vega": "0.5199",
    "rho": "0.1803"
  },
  {
    "date": "2024-02-12",
    "act_symbol": "SPY",
    "expiration": "2024-03-08",
    "strike": "501.00",
    "call_put": "Put",
    "bid": "5.34",
    "ask": "5.37",
    "vol": "0.1111",
    "delta": "-0.4792",
    "gamma": "0.0293",
    "theta": "-0.0882",
    "vega": "0.5169",
    "rho": "-0.1221"
  },
  {
    "date": "2024-02-12",
    "act_symbol": "SPY",
    "expiration": "2024-03-08",
    "strike": "511.00",
    "call_put": "Call",
    "bid": "2.41",
    "ask": "2.42",
    "vol": "0.1090",
    "delta": "0.2778",
    "gamma": "0.0234",
    "theta": "-0.1158",
    "vega": "0.4392",
    "rho": "0.0936"
  },
  {
    "date": "2024-02-12",
    "act_symbol": "SPY",
    "expiration": "2024-03-08",
    "strike": "511.00",
    "call_put": "Put",
    "bid": "11.28",
    "ask": "11.54",
    "vol": "0.1036",
    "delta": "-0.7895",
    "gamma": "0.0290",
    "theta": "-0.0470",
    "vega": "0.3743",
    "rho": "-0.1216"
  },
  {
    "date": "2024-02-12",
    "act_symbol": "SPY",
    "expiration": "2024-03-08",
    "strike": "522.00",
    "call_put": "Call",
    "bid": "0.53",
    "ask": "0.54",
    "vol": "0.1061",
    "delta": "0.0849",
    "gamma": "0.0111",
    "theta": "-0.0494",
    "vega": "0.2036",
    "rho": "0.0287"
  },
  {
    "date": "2024-02-12",
    "act_symbol": "SPY",
    "expiration": "2024-03-08",
    "strike": "522.00",
    "call_put": "Put",
    "bid": "21.39",
    "ask": "21.72",
    "vol": "0.1061",
    "delta": "-1.0000",
    "gamma": "0.0012",
    "theta": "0.0000",
    "vega": "0.0034",
    "rho": "0.0000"
  },
  {
    "date": "2024-02-12",
    "act_symbol": "SPY",
    "expiration": "2024-03-08",
    "strike": "530.00",
    "call_put": "Call",
    "bid": "0.15",
    "ask": "0.16",
    "vol": "0.1074",
    "delta": "0.0288",
    "gamma": "0.0046",
    "theta": "-0.0206",
    "vega": "0.0863",
    "rho": "0.0097"
  },
  {
    "date": "2024-02-12",
    "act_symbol": "SPY",
    "expiration": "2024-03-08",
    "strike": "530.00",
    "call_put": "Put",
    "bid": "29.39",
    "ask": "29.72",
    "vol": "0.1074",
    "delta": "-1.0000",
    "gamma": "0.0000",
    "theta": "0.0000",
    "vega": "0.0000",
    "rho": "0.0000"
  },
  {
    "date": "2024-02-12",
    "act_symbol": "SPY",
    "expiration": "2024-03-08",
    "strike": "540.00",
    "call_put": "Call",
    "bid": "0.05",
    "ask": "0.06",
    "vol": "0.1190",
    "delta": "0.0104",
    "gamma": "0.0017",
    "theta": "-0.0094",
    "vega": "0.0363",
    "rho": "0.0035"
  },
  {
    "date": "2024-02-12",
    "act_symbol": "SPY",
    "expiration": "2024-03-08",
    "strike": "540.00",
    "call_put": "Put",
    "bid": "39.39",
    "ask": "39.72",
    "vol": "0.1190",
    "delta": "-1.0000",
    "gamma": "0.0000",
    "theta": "0.0000",
    "vega": "0.0000",
    "rho": "0.0000"
  },
  {
    "date": "2024-02-12",
    "act_symbol": "SPY",
    "expiration": "2024-03-08",
    "strike": "550.00",
    "call_put": "Call",
    "bid": "0.03",
    "ask": "0.04",
    "vol": "0.1374",
    "delta": "0.0061",
    "gamma": "0.0009",
    "theta": "-0.0066",
    "vega": "0.0226",
    "rho": "0.0020"
  },
  {
    "date": "2024-02-12",
    "act_symbol": "SPY",
    "expiration": "2024-03-08",
    "strike": "550.00",
    "call_put": "Put",
    "bid": "49.38",
    "ask": "49.72",
    "vol": "0.1374",
    "delta": "-1.0000",
    "gamma": "0.0000",
    "theta": "0.0000",
    "vega": "0.0000",
    "rho": "0.0000"
  },
  {
    "date": "2024-02-12",
    "act_symbol": "SPY",
    "expiration": "2024-03-08",
    "strike": "565.00",
    "call_put": "Call",
    "bid": "0.01",
    "ask": "0.02",
    "vol": "0.1632",
    "delta": "0.0031",
    "gamma": "0.0004",
    "theta": "-0.0042",
    "vega": "0.0124",
    "rho": "0.0010"
  },
  {
    "date": "2024-02-12",
    "act_symbol": "SPY",
    "expiration": "2024-03-08",
    "strike": "565.00",
    "call_put": "Put",
    "bid": "64.38",
    "ask": "64.72",
    "vol": "0.1632",
    "delta": "-1.0000",
    "gamma": "0.0000",
    "theta": "0.0000",
    "vega": "0.0000",
    "rho": "0.0000"
  },
  {
    "date": "2024-02-12",
    "act_symbol": "SPY",
    "expiration": "2024-03-08",
    "strike": "570.00",
    "call_put": "Call",
    "bid": "0.01",
    "ask": "0.02",
    "vol": "0.1741",
    "delta": "0.0029",
    "gamma": "0.0003",
    "theta": "-0.0043",
    "vega": "0.0117",
    "rho": "0.0009"
  },
  {
    "date": "2024-02-12",
    "act_symbol": "SPY",
    "expiration": "2024-03-08",
    "strike": "570.00",
    "call_put": "Put",
    "bid": "69.38",
    "ask": "69.72",
    "vol": "0.1741",
    "delta": "-1.0000",
    "gamma": "0.0000",
    "theta": "0.0000",
    "vega": "0.0000",
    "rho": "0.0000"
  },
  {
    "date": "2024-02-12",
    "act_symbol": "SPY",
    "expiration": "2024-03-28",
    "strike": "350.00",
    "call_put": "Call",
    "bid": "152.07",
    "ask": "152.57",
    "vol": "0.5414",
    "delta": "0.9746",
    "gamma": "0.0005",
    "theta": "-0.0786",
    "vega": "0.0949",
    "rho": "0.4131"
  },
  {
    "date": "2024-02-12",
    "act_symbol": "SPY",
    "expiration": "2024-03-28",
    "strike": "350.00",
    "call_put": "Put",
    "bid": "0.12",
    "ask": "0.13",
    "vol": "0.4138",
    "delta": "-0.0051",
    "gamma": "0.0002",
    "theta": "-0.0118",
    "vega": "0.0262",
    "rho": "-0.0033"
  },
  {
    "date": "2024-02-12",
    "act_symbol": "SPY",
    "expiration": "2024-03-28",
    "strike": "364.00",
    "call_put": "Call",
    "bid": "138.18",
    "ask": "138.66",
    "vol": "0.4912",
    "delta": "0.9722",
    "gamma": "0.0006",
    "theta": "-0.0798",
    "vega": "0.1031",
    "rho": "0.4288"
  },
  {
    "date": "2024-02-12",
    "act_symbol": "SPY",
    "expiration": "2024-03-28",
    "strike": "364.00",
    "call_put": "Put",
    "bid": "0.14",
    "ask": "0.16",
    "vol": "0.3812",
    "delta": "-0.0066",
    "gamma": "0.0002",
    "theta": "-0.0134",
    "vega": "0.0325",
    "rho": "-0.0042"
  },
  {
    "date": "2024-02-12",
    "act_symbol": "SPY",
    "expiration": "2024-03-28",
    "strike": "375.00",
    "call_put": "Call",
    "bid": "127.26",
    "ask": "127.73",
    "vol": "0.4524",
    "delta": "0.9701",
    "gamma": "0.0007",
    "theta": "-0.0804",
    "vega": "0.1102",
    "rho": "0.4410"
  },
  {
    "date": "2024-02-12",
    "act_symbol": "SPY",
    "expiration": "2024-03-28",
    "strike": "375.00",
    "call_put": "Put",
    "bid": "0.18",
    "ask": "0.19",
    "vol": "0.3587",
    "delta": "-0.0084",
    "gamma": "0.0003",
    "theta": "-0.0157",
    "vega": "0.0404",
    "rho": "-0.0054"
  },
  {
    "date": "2024-02-12",
    "act_symbol": "SPY",
    "expiration": "2024-03-28",
    "strike": "390.00",
    "call_put": "Call",
    "bid": "112.38",
    "ask": "112.86",
    "vol": "0.4026",
    "delta": "0.9663",
    "gamma": "0.0009",
    "theta": "-0.0820",
    "vega": "0.1230",
    "rho": "0.4569"
  },
  {
    "date": "2024-02-12",
    "act_symbol": "SPY",
    "expiration": "2024-03-28",
    "strike": "390.00",
    "call_put": "Put",
    "bid": "0.23",
    "ask": "0.25",
    "vol": "0.3268",
    "delta": "-0.0116",
    "gamma": "0.0005",
    "theta": "-0.0189",
    "vega": "0.0535",
    "rho": "-0.0075"
  },
  {
    "date": "2024-02-12",
    "act_symbol": "SPY",
    "expiration": "2024-03-28",
    "strike": "401.00",
    "call_put": "Call",
    "bid": "101.49",
    "ask": "101.95",
    "vol": "0.3673",
    "delta": "0.9627",
    "gamma": "0.0011",
    "theta": "-0.0834",
    "vega": "0.1347",
    "rho": "0.4681"
  },
  {
    "date": "2024-02-12",
    "act_symbol": "SPY",
    "expiration": "2024-03-28",
    "strike": "401.00",
    "call_put": "Put",
    "bid": "0.28",
    "ask": "0.30",
    "vol": "0.3031",
    "delta": "-0.0148",
    "gamma": "0.0007",
    "theta": "-0.0215",
    "vega": "0.0658",
    "rho": "-0.0095"
  },
  {
    "date": "2024-02-12",
    "act_symbol": "SPY",
    "expiration": "2024-03-28",
    "strike": "413.00",
    "call_put": "Call",
    "bid": "89.61",
    "ask": "90.07",
    "vol": "0.3297",
    "delta": "0.9576",
    "gamma": "0.0014",
    "theta": "-0.0851",
    "vega": "0.1505",
    "rho": "0.4796"
  },
  {
    "date": "2024-02-12",
    "act_symbol": "SPY",
    "expiration": "2024-03-28",
    "strike": "413.00",
    "call_put": "Put",
    "bid": "0.36",
    "ask": "0.37",
    "vol": "0.2780",
    "delta": "-0.0197",
    "gamma": "0.0009",
    "theta": "-0.0250",
    "vega": "0.0840",
    "rho": "-0.0126"
  },
  {
    "date": "2024-02-12",
    "act_symbol": "SPY",
    "expiration": "2024-03-28",
    "strike": "426.00",
    "call_put": "Call",
    "bid": "76.77",
    "ask": "77.23",
    "vol": "0.2907",
    "delta": "0.9499",
    "gamma": "0.0019",
    "theta": "-0.0876",
    "vega": "0.1735",
    "rho": "0.4907"
  },
  {
    "date": "2024-02-12",
    "act_symbol": "SPY",
    "expiration": "2024-03-28",
    "strike": "426.00",
    "call_put": "Put",
    "bid": "0.47",
    "ask": "0.49",
    "vol": "0.2511",
    "delta": "-0.0275",
    "gamma": "0.0014",
    "theta": "-0.0297",
    "vega": "0.1112",
    "rho": "-0.0175"
  },
  {
    "date": "2024-02-12",
    "act_symbol": "SPY",
    "expiration": "2024-03-28",
    "strike": "438.00",
    "call_put": "Call",
    "bid": "64.97",
    "ask": "65.42",
    "vol": "0.2565",
    "delta": "0.9394",
    "gamma": "0.0025",
    "theta": "-0.0908",
    "vega": "0.2036",
    "rho": "0.4987"
  },
  {
    "date": "2024-02-12",
    "act_symbol": "SPY",
    "expiration": "2024-03-28",
    "strike": "438.00",
    "call_put": "Put",
    "bid": "0.62",
    "ask": "0.64",
    "vol": "0.2262",
    "delta": "-0.0382",
    "gamma": "0.0020",
    "theta": "-0.0350",
    "vega": "0.1530",
    "rho": "-0.0227"
  },
  {
    "date": "2024-02-12",
    "act_symbol": "SPY",
    "expiration": "2024-03-28",
    "strike": "451.00",
    "call_put": "Call",
    "bid": "52.28",
    "ask": "52.72",
    "vol": "0.2215",
    "delta": "0.9210",
    "gamma": "0.0036",
    "theta": "-0.0958",
    "vega": "0.2519",
    "rho": "0.5031"
  },
  {
    "date": "2024-02-12",
    "act_symbol": "SPY",
    "expiration": "2024-03-28",
    "strike": "451.00",
    "call_put": "Put",
    "bid": "0.89",
    "ask": "0.91",
    "vol": "0.2004",
    "delta": "-0.0579",
    "gamma": "0.0033",
    "theta": "-0.0428",
    "vega": "0.2128",
    "rho": "-0.0340"
  },
  {
    "date": "2024-02-12",
    "act_symbol": "SPY",
    "expiration": "2024-03-28",
    "strike": "461.00",
    "call_put": "Call",
    "bid": "42.63",
    "ask": "43.06",
    "vol": "0.1960",
    "delta": "0.8984",
    "gamma": "0.0050",
    "theta": "-0.1008",
    "vega": "0.3056",
    "rho": "0.5010"
  },
  {
    "date": "2024-02-12",
    "act_symbol": "SPY",
    "expiration": "2024-03-28",
    "strike": "461.00",
    "call_put": "Put",
    "bid": "1.22",
    "ask": "1.24",
    "vol": "0.1809",
    "delta": "-0.0826",
    "gamma": "0.0048",
    "theta": "-0.0502",
    "vega": "0.2832",
    "rho": "-0.0478"
  },
  {
    "date": "2024-02-12",
    "act_symbol": "SPY",
    "expiration": "2024-03-28",
    "strike": "471.00",
    "call_put": "Call",
    "bid": "33.19",
    "ask": "33.60",
    "vol": "0.1726",
    "delta": "0.8616",
    "gamma": "0.0071",
    "theta": "-0.1073",
    "vega": "0.3826",
    "rho": "0.4899"
  },
  {
    "date": "2024-02-12",
    "act_symbol": "SPY",
    "expiration": "2024-03-28",
    "strike": "471.00",
    "call_put": "Put",
    "bid": "1.76",
    "ask": "1.78",
    "vol": "0.1620",
    "delta": "-0.1227",
    "gamma": "0.0072",
    "theta": "-0.0590",
    "vega": "0.3643",
    "rho": "-0.0699"
  },
  {
    "date": "2024-02-12",
    "act_symbol": "SPY",
    "expiration": "2024-03-28",
    "strike": "481.00",
    "call_put": "Call",
    "bid": "24.15",
    "ask": "24.50",
    "vol": "0.1515",
    "delta": "0.7996",
    "gamma": "0.0104",
    "theta": "-0.1146",
    "vega": "0.4879",
    "rho": "0.4629"
  },
  {
    "date": "2024-02-12",
    "act_symbol": "SPY",
    "expiration": "2024-03-28",
    "strike": "481.00",
    "call_put": "Put",
    "bid": "2.69",
    "ask": "2.71",
    "vol": "0.1443",
    "delta": "-0.1897",
    "gamma": "0.0108",
    "theta": "-0.0685",
    "vega": "0.4883",
    "rho": "-0.1050"
  },
  {
    "date": "2024-02-12",
    "act_symbol": "SPY",
    "expiration": "2024-03-28",
    "strike": "491.00",
    "call_put": "Call",
    "bid": "15.81",
    "ask": "16.13",
    "vol": "0.1328",
    "delta": "0.6960",
    "gamma": "0.0149",
    "theta": "-0.1192",
    "vega": "0.6110",
    "rho": "0.4094"
  },
  {
    "date": "2024-02-12",
    "act_symbol": "SPY",
    "expiration": "2024-03-28",
    "strike": "491.00",
    "call_put": "Put",
    "bid": "4.40",
    "ask": "4.43",
    "vol": "0.1287",
    "delta": "-0.3025",
    "gamma": "0.0158",
    "theta": "-0.0756",
    "vega": "0.6145",
    "rho": "-0.1593"
  },
  {
    "date": "2024-02-12",
    "act_symbol": "SPY",
    "expiration": "2024-03-28",
    "strike": "501.00",
    "call_put": "Call",
    "bid": "9.02",
    "ask": "9.07",
    "vol": "0.1189",
    "delta": "0.5347",
    "gamma": "0.0189",
    "theta": "-0.1148",
    "vega": "0.6960",
    "rho": "0.3184"
  },
  {
    "date": "2024-02-12",
    "act_symbol": "SPY",
    "expiration": "2024-03-28",
    "strike": "501.00",
    "call_put": "Put",
    "bid": "7.61",
    "ask": "7.64",
    "vol": "0.1167",
    "delta": "-0.4772",
    "gamma": "0.0204",
    "theta": "-0.0730",
    "vega": "0.6938",
    "rho": "-0.2265"
  },
  {
    "date": "2024-02-12",
    "act_symbol": "SPY",
    "expiration": "2024-03-28",
    "strike": "511.00",
    "call_put": "Call",
    "bid": "4.35",
    "ask": "4.39",
    "vol": "0.1121",
    "delta": "0.3404",
    "gamma": "0.0185",
    "theta": "-0.0948",
    "vega": "0.6428",
    "rho": "0.2044"
  },
  {
    "date": "2024-02-12",
    "act_symbol": "SPY",
    "expiration": "2024-03-28",
    "strike": "511.00",
    "call_put": "Put",
    "bid": "12.98",
    "ask": "13.23",
    "vol": "0.1095",
    "delta": "-0.6932",
    "gamma": "0.0210",
    "theta": "-0.0533",
    "vega": "0.6065",
    "rho": "-0.2583"
  },
  {
    "date": "2024-02-12",
    "act_symbol": "SPY",
    "expiration": "2024-03-28",
    "strike": "521.00",
    "call_put": "Call",
    "bid": "1.78",
    "ask": "1.81",
    "vol": "0.1091",
    "delta": "0.1765",
    "gamma": "0.0135",
    "theta": "-0.0628",
    "vega": "0.4548",
    "rho": "0.1066"
  },
  {
    "date": "2024-02-12",
    "act_symbol": "SPY",
    "expiration": "2024-03-28",
    "strike": "521.00",
    "call_put": "Put",
    "bid": "20.72",
    "ask": "21.08",
    "vol": "0.1039",
    "delta": "-0.8980",
    "gamma": "0.0170",
    "theta": "-0.0195",
    "vega": "0.3274",
    "rho": "-0.1506"
  },
  {
    "date": "2024-02-12",
    "act_symbol": "SPY",
    "expiration": "2024-03-28",
    "strike": "532.00",
    "call_put": "Call",
    "bid": "0.57",
    "ask": "0.59",
    "vol": "0.1088",
    "delta": "0.0696",
    "gamma": "0.0069",
    "theta": "-0.0314",
    "vega": "0.2348",
    "rho": "0.0422"
  },
  {
    "date": "2024-02-12",
    "act_symbol": "SPY",
    "expiration": "2024-03-28",
    "strike": "532.00",
    "call_put": "Put",
    "bid": "31.34",
    "ask": "31.78",
    "vol": "0.1088",
    "delta": "-1.0000",
    "gamma": "0.0010",
    "theta": "0.0000",
    "vega": "0.0081",
    "rho": "0.0000"
  },
  {
    "date": "2024-02-12",
    "act_symbol": "SPY",
    "expiration": "2024-03-28",
    "strike": "542.00",
    "call_put": "Call",
    "bid": "0.19",
    "ask": "0.21",
    "vol": "0.1111",
    "delta": "0.0271",
    "gamma": "0.0032",
    "theta": "-0.0147",
    "vega": "0.1100",
    "rho": "0.0165"
  },
  {
    "date": "2024-02-12",
    "act_symbol": "SPY",
    "expiration": "2024-03-28",
    "strike": "542.00",
    "call_put": "Put",
    "bid": "41.33",
    "ask": "41.78",
    "vol": "0.1111",
    "delta": "-1.0000",
    "gamma": "0.0000",
    "theta": "0.0000",
    "vega": "0.0000",
    "rho": "0.0000"
  },
  {
    "date": "2024-02-12",
    "act_symbol": "SPY",
    "expiration": "2024-03-28",
    "strike": "550.00",
    "call_put": "Call",
    "bid": "0.09",
    "ask": "0.10",
    "vol": "0.1155",
    "delta": "0.0135",
    "gamma": "0.0017",
    "theta": "-0.0084",
    "vega": "0.0608",
    "rho": "0.0082"
  },
  {
    "date": "2024-02-12",
    "act_symbol": "SPY",
    "expiration": "2024-03-28",
    "strike": "550.00",
    "call_put": "Put",
    "bid": "49.33",
    "ask": "49.78",
    "vol": "0.1155",
    "delta": "-1.0000",
    "gamma": "0.0000",
    "theta": "0.0000",
    "vega": "0.0000",
    "rho": "0.0000"
  },
  {
    "date": "2024-02-12",
    "act_symbol": "SPY",
    "expiration": "2024-03-28",
    "strike": "565.00",
    "call_put": "Call",
    "bid": "0.03",
    "ask": "0.06",
    "vol": "0.1322",
    "delta": "0.0060",
    "gamma": "0.0007",
    "theta": "-0.0047",
    "vega": "0.0302",
    "rho": "0.0037"
  },
  {
    "date": "2024-02-12",
    "act_symbol": "SPY",
    "expiration": "2024-03-28",
    "strike": "565.00",
    "call_put": "Put",
    "bid": "64.33",
    "ask": "64.78",
    "vol": "0.1322",
    "delta": "-1.0000",
    "gamma": "0.0000",
    "theta": "0.0000",
    "vega": "0.0000",
    "rho": "0.0000"
  },
  {
    "date": "2024-02-12",
    "act_symbol": "SPY",
    "expiration": "2024-03-28",
    "strike": "575.00",
    "call_put": "Call",
    "bid": "0.03",
    "ask": "0.04",
    "vol": "0.1455",
    "delta": "0.0044",
    "gamma": "0.0005",
    "theta": "-0.0038",
    "vega": "0.0228",
    "rho": "0.0026"
  },
  {
    "date": "2024-02-12",
    "act_symbol": "SPY",
    "expiration": "2024-03-28",
    "strike": "575.00",
    "call_put": "Put",
    "bid": "74.33",
    "ask": "74.78",
    "vol": "0.1455",
    "delta": "-1.0000",
    "gamma": "0.0000",
    "theta": "0.0000",
    "vega": "0.0000",
    "rho": "0.0000"
  },
  {
    "date": "2024-02-12",
    "act_symbol": "SPY",
    "expiration": "2024-03-28",
    "strike": "590.00",
    "call_put": "Call",
    "bid": "0.01",
    "ask": "0.03",
    "vol": "0.1673",
    "delta": "0.0034",
    "gamma": "0.0003",
    "theta": "-0.0034",
    "vega": "0.0179",
    "rho": "0.0020"
  },
  {
    "date": "2024-02-12",
    "act_symbol": "SPY",
    "expiration": "2024-03-28",
    "strike": "590.00",
    "call_put": "Put",
    "bid": "89.32",
    "ask": "89.78",
    "vol": "0.1673",
    "delta": "-1.0000",
    "gamma": "0.0000",
    "theta": "0.0000",
    "vega": "0.0000",
    "rho": "0.0000"
  }
]